maci/__init__.py
maci/__init__.pyi
maci/data.py
maci/data.pyi
maci/error.py
maci/hint.py
maci/hint.pyi
maci/py.typed
maci/_hash/comparefilehash.py
maci/_hash/createfilehash.py
maci/_hash/createhash.py
maci/_ini/inibuildauto.py
maci/_ini/inibuildmanual.py
maci/_ini/inidump.py
maci/_ini/iniload.py
maci/_json/jsondump.py
maci/_json/jsondumpstr.py
maci/_json/jsonload.py
maci/_json/jsonloadstr.py
maci/_native/build.py
maci/_native/cleanformat.py
maci/_native/dump.py
maci/_native/dumpraw.py
maci/_native/dumpstr.py
maci/_native/load.py
maci/_native/loadattrs.py
maci/_native/loaddict.py
maci/_native/loadraw.py
maci/_native/loadstr.py
maci/_native/loadstrdict.py
maci/_pickle/pickledumpbytes.py
maci/_pickle/pickleloadbytes.py
maci/_toml/tomldump.py
maci/_toml/tomldumpstr.py
maci/_toml/tomlload.py
maci/_toml/tomlloadstr.py
maci/_xml/xmlbuildmanual.py
maci/_xml/xmldump.py
maci/_xml/xmldumpdict.py
maci/_xml/xmldumpstr.py
maci/_xml/xmldumpstrdict.py
maci/_xml/xmlload.py
maci/_xml/xmlloaddict.py
maci/_xml/xmlloadstr.py
maci/_xml/xmlloadstrdict.py
maci/_yaml/yamldump.py
maci/_yaml/yamldumpall.py
maci/_yaml/yamldumpstr.py
maci/_yaml/yamlload.py
maci/_yaml/yamlloadall.py
maci/_yaml/yamlloadstr.py
maci/ext/defusedxml/LICENSE.txt
maci-1.1.0.dist-info/METADATA
maci-1.1.0.dist-info/WHEEL
maci-1.1.0.dist-info/top_level.txt
maci-1.1.0.dist-info/RECORD
