Metadata-Version: 2.1
Name: maci
Version: 1.1.0
Summary: The easy to use library for your data, configuration, and save files
Author: aaronater10
Author-email: dev_admin@dunnts.com
License: MIT
Project-URL: Docs, https://docs.macilib.org
Project-URL: Code, https://github.com/aaronater10/maci
Project-URL: Bugs, https://github.com/aaronater10/maci/issues
Project-URL: CI, https://github.com/aaronater10/maci/actions
Keywords: maci,aaronater10,python,py,config,file,export,parse,text file,cfg,conf,save file,config file,db,database,simple,configuration,alternative,safe,ini,json,xml,yml,data,import
Classifier: Development Status :: 5 - Production/Stable
Classifier: Intended Audience :: Developers
Classifier: Intended Audience :: System Administrators
Classifier: Intended Audience :: Information Technology
Classifier: Programming Language :: Python :: 3
Classifier: Programming Language :: Python :: 3.8
Classifier: Programming Language :: Python :: 3.9
Classifier: Programming Language :: Python :: 3.10
Classifier: Programming Language :: Python :: 3.11
Classifier: Programming Language :: Python :: 3.12
Classifier: Operating System :: POSIX :: Linux
Classifier: Operating System :: Microsoft :: Windows
Classifier: Operating System :: MacOS :: MacOS X
Requires-Python: >=3.8
Requires-Dist: pyyaml>=5.4
Requires-Dist: tomli>=2.0.1
Requires-Dist: tomli-w>=1.0.0
Requires-Dist: defusedxml>=0.7.1
Requires-Dist: xmltodict>=0.13.0
